simple_config_sync/__init__.py
simple_config_sync/__main__.py
simple_config_sync/py.typed
simple_config_sync/core/__init__.py
simple_config_sync/core/backup.py
simple_config_sync/core/cli.py
simple_config_sync/core/config.py
simple_config_sync/core/tui.py
simple_config_sync/core/assets/tui.tcss
simple_config_sync-0.1.24.dist-info/METADATA
simple_config_sync-0.1.24.dist-info/WHEEL
simple_config_sync-0.1.24.dist-info/entry_points.txt
simple_config_sync-0.1.24.dist-info/licenses/LICENSE
simple_config_sync-0.1.24.dist-info/RECORD
