Metadata-Version: 2.4
Name: simple-config-sync
Version: 0.1.24
Summary: This tool is used to synchronize dotfiles across various Linux devices, with capabilities to automatically create and delete links, as well as selectively synchronize files.
Project-URL: Repository, https://github.com/hmeqo/simple-config-sync.git
Project-URL: Issues, https://github.com/hmeqo/simple-config-sync/issues
License: MIT License
License-File: LICENSE
Keywords: config,dotfiles
Classifier: Programming Language :: Python
Requires-Python: >=3.11
Requires-Dist: click>=8.1.7
Requires-Dist: mmh3>=4.1.0
Requires-Dist: textual>=0.52.1
Requires-Dist: toml>=0.10.2
